dlapp/__init__.py
dlapp/__main__.py
dlapp/application.py
dlapp/argumenthelper.py
dlapp/collection.py
dlapp/config.py
dlapp/dlquery.py
dlapp/exceptions.py
dlapp/factory.py
dlapp/main.py
dlapp/parser.py
dlapp/predicate.py
dlapp/tutorial.py
dlapp/utils.py
dlapp/validation.py
dlapp-0.3.6.dist-info/LICENSE
dlapp-0.3.6.dist-info/METADATA
dlapp-0.3.6.dist-info/WHEEL
dlapp-0.3.6.dist-info/entry_points.txt
dlapp-0.3.6.dist-info/top_level.txt
dlapp-0.3.6.dist-info/RECORD
